{
  "openapi": "3.0.0",
  "info": {
    "title": "RentX Documentation",
    "description": "This is an API Rent",
    "version": "1.0.0",
    "contact": {
      "email": "rntlomba@gmail.com"
    }
  },
  "paths": {
    "/categories": {
      "post": {
        "tags": ["Categories"],
        "summary": "Create a category",
        "description": "Create a new category",
        "security": [
          { "bearerAuth": [] }
        ],
        "requestBody": {
          "content": {
            "application/json": {
              "schema": {
                "type": "object",
                "properties": {
                  "name": {
                    "type": "string"
                  },
                  "description": {
                    "type": "string"
                  }
                },
                "example": {
                  "name": "category name sample",
                  "description": "category description sample"
                }
              }
            }
          }
        },
        "responses": {
          "201": {
            "description": "Created"
          },
          "500": {
            "description": "Category already exists"
          }
        }
      },
      "get": {
        "tags": ["Categories"],
        "summary": "List categories",
        "description": "List all categories created",
        "responses": {
          "200": {
            "description": "Success",
            "content": {
              "application/json":{
                "schema": {
                  "type": "array",
                  "items": {
                    "type": "object",
                    "properties": {
                      "name": {
                        "type": "string"
                      },
                      "description": {
                        "type": "string"
                      },
                      "id": {
                        "type": "string"
                      },
                      "created_at": {
                        "type": "string"
                      }
                    }
                  }
                }
              }
            }
          }
        }
      }
    },
    "/categories/import": {
      "post": {
        "tags": ["Categories"],
        "summary": "Upload categories",
        "description": "Upload new categories by a .csv file",
        "requestBody": {
          "content": {
            "multipart/form-data": {
              "schema": {
                "type": "object",
                "properties": {
                  "file": {
                    "type": "string",
                    "format": "binary"
                  }
                }
              }
            }
          }
        },
        "responses": {
          "201": {
            "description": "Created"
          }
        }
      }
    },
    "/specifications": {
      "post": {
        "tags": ["Specifications"],
        "summary": "Create a specification",
        "description": "Create a new specification",
        "requestBody": {
          "content": {
            "application/json": {
              "schema": {
                "$ref": "#/definitions/Specification"
              }
            }
          }
        },
        "responses": {
          "201": {
            "description": "Created"
          },
          "500": {
            "description": "Specification already exists!"
          }
        }
      }
    },
    "/auth/sessions": {
      "post": {
        "tags": ["Session"],
        "summary": "Authenticate session",
        "description": "Authenticate session",
        "requestBody": {
          "content": {
            "application/json": {
              "schema": {
                "type": "object",
                "properties": {
                  "email": {
                    "type": "string"
                  },
                  "password": {
                    "type": "string"
                  }
                }
              }
            }
          }
        },
        "responses": {
          "200": {
            "description": "Success"
          },
          "400": {
            "description": "Email or password is incorrect"
          }
        }
      }
    }
  },
  "definitions": {
    "Specification": {
      "type": "object",
      "properties": {
        "name": {
          "type": "string"
        },
        "description": {
          "type": "string"
        }
      }
    }
  },
  "components": {
    "securitySchemes": {
      "bearerAuth": {
        "type": "http",
        "scheme": "bearer",
        "bearerFormat": "JWT"
      }
    }
  }
}
